Metadata-Version: 1.1
Name: openlmi-scripts-locale
Version: 0.4.0
Summary: LMI command for system locale administration.
Home-page: https://github.com/openlmi/openlmi-locale
Author: Vitezslav Crhonek
Author-email: vcrhonek@redhat.com
License: BSD
Download-URL: https://github.com/openlmi/openlmi-locale/tarball/master
Platform: Any
Classifier: License :: OSI Approved :: BSD License
Classifier: Operating System :: POSIX :: Linux
Classifier: Topic :: System :: Systems Administration
Classifier: Programming Language :: Python
Classifier: Programming Language :: Python :: 2
Classifier: Programming Language :: Python :: 2.7
Classifier: Intended Audience :: Developers
Classifier: Environment :: Console
